BatchFiltering.py
BatchFiltering-0.0.2.dist-info/LICENSE
BatchFiltering-0.0.2.dist-info/METADATA
BatchFiltering-0.0.2.dist-info/WHEEL
BatchFiltering-0.0.2.dist-info/top_level.txt
BatchFiltering-0.0.2.dist-info/RECORD
