Metadata-Version: 2.1
Name: BatchFiltering
Version: 0.0.2
Summary: Batch filtering for generative adversarial networks
Home-page: https://github.com/shanfenghu/BatchFiltering
Author: Shanfeng Hu
Author-email: shanfeng.hu1991@gmail.com
License: UNKNOWN
Platform: UNKNOWN
Classifier: Programming Language :: Python :: 3
Classifier: License :: OSI Approved :: MIT License
Classifier: Operating System :: OS Independent
Requires-Python: >=3.7
